labx_rs-0.2.0.dist-info/METADATA
labx_rs-0.2.0.dist-info/WHEEL
labx.libs/libbz2-c1f89286.so.1.0
labx/__init__.py
labx/labx.cpython-311-x86_64-linux-gnu.so
labx_rs-0.2.0.dist-info/RECORD
