Metadata-Version: 2.1
Name: labx-rs
Version: 0.2.0
